SmplScript/__init__.py
SmplScript/run.py
SmplScript/strings_with_arrows.py
SmplScript-0.1.3.1.dist-info/LICENCE
SmplScript-0.1.3.1.dist-info/METADATA
SmplScript-0.1.3.1.dist-info/WHEEL
SmplScript-0.1.3.1.dist-info/entry_points.txt
SmplScript-0.1.3.1.dist-info/top_level.txt
SmplScript-0.1.3.1.dist-info/RECORD
