Metadata-Version: 2.1
Name: SmplScript
Version: 0.1.3.1
Summary: A language written from python, meant for beginners
Home-page: https://github.com/CubesandSLEIGHTS/SmplScript
Author: Stephen Steyaert
Author-email: stephen.a.steyaert@gmail.com
License: GNU General Public v2
Platform: UNKNOWN
Classifier: License :: OSI Approved :: GNU General Public License v2 (GPLv2)
Classifier: Programming Language :: Python :: 3
Classifier: Programming Language :: Python :: 3.7
Requires-Dist: termcolor
